[{"wa": "1.2", "submitting_tests": 0, "tot_running_jobs": 0, "cpu_load": "0.32 0.20 0.09 1/187 30398", "used_mem_proc": 396.60000000000002, "running_tests": 0, "hostname": "hammercloud-ai-15.cern.ch", "tot_queued_jobs": 0, "mem_buffers": "239", "mem_without_bc": "530", "used_mem_HCpythonproc": 25.0, "used_mem": "2903", "used_mem_HCshellproc": 0, "mem_cached": "2133", "timestamp": "2014/07/17 - 13:47:23"}, {"wa": "1.2", "submitting_tests": 0, "tot_running_jobs": 0, "cpu_load": "0.29 0.20 0.09 1/187 30463", "used_mem_proc": 396.60000000000002, "running_tests": 0, "hostname": "hammercloud-ai-15.cern.ch", "tot_queued_jobs": 0, "mem_buffers": "239", "mem_without_bc": "530", "used_mem_HCpythonproc": 25.0, "used_mem": "2903", "used_mem_HCshellproc": 0, "mem_cached": "2133", "timestamp": "2014/07/17 - 13:47:29"}, {"wa": "1.2", "submitting_tests": 0, "tot_running_jobs": 0, "cpu_load": "0.30 0.21 0.11 2/194 30696", "used_mem_proc": 406.80000000000001, "running_tests": 0, "hostname": "hammercloud-ai-15.cern.ch", "tot_queued_jobs": 0, "mem_buffers": "239", "mem_without_bc": "560", "used_mem_HCpythonproc": 37.200000000000003, "used_mem": "2932", "used_mem_HCshellproc": 0.52200000000000002, "mem_cached": "2133", "timestamp": "2014/07/17 - 13:51:01"}, {"wa": "1.2", "submitting_tests": 0, "tot_running_jobs": 0, "cpu_load": "0.45 0.16 0.11 2/196 31341", "used_mem_proc": 420.5, "running_tests": 0, "hostname": "hammercloud-ai-15.cern.ch", "tot_queued_jobs": 0, "mem_buffers": "239", "mem_without_bc": "542", "used_mem_HCpythonproc": 51.799999999999997, "used_mem": "2911", "used_mem_HCshellproc": 0.52200000000000002, "mem_cached": "2133", "timestamp": "2014/07/17 - 14:01:02"}, {"wa": "1.2", "submitting_tests": 0, "tot_running_jobs": 0, "cpu_load": "0.09 0.14 0.10 2/193 31832", "used_mem_proc": 397.19999999999999, "running_tests": 0, "hostname": "hammercloud-ai-15.cern.ch", "tot_queued_jobs": 0, "mem_buffers": "239", "mem_without_bc": "552", "used_mem_HCpythonproc": 29.600000000000001, "used_mem": "2924", "used_mem_HCshellproc": 0.51900000000000002, "mem_cached": "2133", "timestamp": "2014/07/17 - 14:11:02"}, {"wa": "1.2", "submitting_tests": 0, "tot_running_jobs": 0, "cpu_load": "0.63 0.18 0.10 3/193 32374", "used_mem_proc": 397.10000000000002, "running_tests": 0, "hostname": "hammercloud-ai-15.cern.ch", "tot_queued_jobs": 0, "mem_buffers": "239", "mem_without_bc": "558", "used_mem_HCpythonproc": 36.399999999999999, "used_mem": "2930", "used_mem_HCshellproc": 0.51900000000000002, "mem_cached": "2133", "timestamp": "2014/07/17 - 14:21:01"}, {"wa": "1.2", "submitting_tests": 0, "tot_running_jobs": 0, "cpu_load": "0.21 0.25 0.15 4/194 1325", "used_mem_proc": 397.5, "running_tests": 0, "hostname": "hammercloud-ai-15.cern.ch", "tot_queued_jobs": 0, "mem_buffers": "239", "mem_without_bc": "559", "used_mem_HCpythonproc": 36.899999999999999, "used_mem": "2932", "used_mem_HCshellproc": 0.52700000000000002, "mem_cached": "2134", "timestamp": "2014/07/17 - 14:31:02"}, {"wa": "1.2", "submitting_tests": 0, "tot_running_jobs": 0, "cpu_load": "0.29 0.14 0.10 2/194 1832", "used_mem_proc": 397.39999999999998, "running_tests": 0, "hostname": "hammercloud-ai-15.cern.ch", "tot_queued_jobs": 0, "mem_buffers": "239", "mem_without_bc": "559", "used_mem_HCpythonproc": 34.799999999999997, "used_mem": "2932", "used_mem_HCshellproc": 0.52700000000000002, "mem_cached": "2134", "timestamp": "2014/07/17 - 14:41:01"}, {"wa": "1.2", "submitting_tests": 0, "tot_running_jobs": 0, "cpu_load": "0.19 0.08 0.08 4/194 2349", "used_mem_proc": 397.5, "running_tests": 0, "hostname": "hammercloud-ai-15.cern.ch", "tot_queued_jobs": 0, "mem_buffers": "239", "mem_without_bc": "559", "used_mem_HCpythonproc": 37.0, "used_mem": "2932", "used_mem_HCshellproc": 0.52300000000000002, "mem_cached": "2134", "timestamp": "2014/07/17 - 14:51:02"}, {"wa": "1.2", "submitting_tests": 0, "tot_running_jobs": 0, "cpu_load": "0.04 0.03 0.04 3/195 2888", "used_mem_proc": 408.69999999999999, "running_tests": 0, "hostname": "hammercloud-ai-15.cern.ch", "tot_queued_jobs": 0, "mem_buffers": "239", "mem_without_bc": "559", "used_mem_HCpythonproc": 47.600000000000001, "used_mem": "2933", "used_mem_HCshellproc": 0.52200000000000002, "mem_cached": "2134", "timestamp": "2014/07/17 - 15:01:03"}, {"wa": "1.2", "submitting_tests": 0, "tot_running_jobs": 0, "cpu_load": "0.11 0.03 0.01 8/198 3491", "used_mem_proc": 469.39999999999998, "running_tests": 0, "hostname": "hammercloud-ai-15.cern.ch", "tot_queued_jobs": 0, "mem_buffers": "239", "mem_without_bc": "586", "used_mem_HCpythonproc": 50.100000000000001, "used_mem": "2960", "used_mem_HCshellproc": 0.51800000000000002, "mem_cached": "2134", "timestamp": "2014/07/17 - 15:11:02"}, {"wa": "1.2", "submitting_tests": 0, "tot_running_jobs": 0, "cpu_load": "0.12 0.12 0.08 3/194 4862", "used_mem_proc": 397.39999999999998, "running_tests": 0, "hostname": "hammercloud-ai-15.cern.ch", "tot_queued_jobs": 0, "mem_buffers": "239", "mem_without_bc": "558", "used_mem_HCpythonproc": 33.299999999999997, "used_mem": "2933", "used_mem_HCshellproc": 0.51900000000000002, "mem_cached": "2135", "timestamp": "2014/07/17 - 15:21:02"}, {"wa": "1.2", "submitting_tests": 0, "tot_running_jobs": 0, "cpu_load": "0.03 0.03 0.03 6/193 5370", "used_mem_proc": 405.19999999999999, "running_tests": 0, "hostname": "hammercloud-ai-15.cern.ch", "tot_queued_jobs": 0, "mem_buffers": "239", "mem_without_bc": "559", "used_mem_HCpythonproc": 36.5, "used_mem": "2933", "used_mem_HCshellproc": 0.52300000000000002, "mem_cached": "2135", "timestamp": "2014/07/17 - 15:31:02"}, {"wa": "1.2", "submitting_tests": 0, "tot_running_jobs": 0, "cpu_load": "0.17 0.10 0.07 3/193 5858", "used_mem_proc": 403.0, "running_tests": 0, "hostname": "hammercloud-ai-15.cern.ch", "tot_queued_jobs": 0, "mem_buffers": "239", "mem_without_bc": "559", "used_mem_HCpythonproc": 32.399999999999999, "used_mem": "2933", "used_mem_HCshellproc": 0.52300000000000002, "mem_cached": "2135", "timestamp": "2014/07/17 - 15:41:02"}, {"wa": "1.2", "submitting_tests": 0, "tot_running_jobs": 0, "cpu_load": "0.22 0.07 0.04 2/193 6352", "used_mem_proc": 403.0, "running_tests": 0, "hostname": "hammercloud-ai-15.cern.ch", "tot_queued_jobs": 0, "mem_buffers": "239", "mem_without_bc": "558", "used_mem_HCpythonproc": 32.700000000000003, "used_mem": "2933", "used_mem_HCshellproc": 0.51900000000000002, "mem_cached": "2135", "timestamp": "2014/07/17 - 15:51:01"}, {"wa": "1.2", "submitting_tests": 0, "tot_running_jobs": 0, "cpu_load": "0.14 0.18 0.10 5/193 8084", "used_mem_proc": 397.19999999999999, "running_tests": 0, "hostname": "hammercloud-ai-15.cern.ch", "tot_queued_jobs": 0, "mem_buffers": "239", "mem_without_bc": "560", "used_mem_HCpythonproc": 36.399999999999999, "used_mem": "2934", "used_mem_HCshellproc": 0.52300000000000002, "mem_cached": "2136", "timestamp": "2014/07/17 - 16:01:02"}, {"wa": "1.2", "submitting_tests": 0, "tot_running_jobs": 0, "cpu_load": "0.32 0.18 0.11 5/193 8619", "used_mem_proc": 408.60000000000002, "running_tests": 0, "hostname": "hammercloud-ai-15.cern.ch", "tot_queued_jobs": 0, "mem_buffers": "239", "mem_without_bc": "559", "used_mem_HCpythonproc": 37.700000000000003, "used_mem": "2936", "used_mem_HCshellproc": 0.51900000000000002, "mem_cached": "2139", "timestamp": "2014/07/17 - 16:11:04"}, {"wa": "1.2", "submitting_tests": 0, "tot_running_jobs": 0, "cpu_load": "0.38 0.23 0.13 3/193 9164", "used_mem_proc": 403.80000000000001, "running_tests": 0, "hostname": "hammercloud-ai-15.cern.ch", "tot_queued_jobs": 0, "mem_buffers": "239", "mem_without_bc": "533", "used_mem_HCpythonproc": 35.0, "used_mem": "2917", "used_mem_HCshellproc": 0.52300000000000002, "mem_cached": "2139", "timestamp": "2014/07/17 - 16:21:02"}, {"wa": "1.2", "submitting_tests": 0, "tot_running_jobs": 0, "cpu_load": "0.10 0.09 0.09 4/194 9665", "used_mem_proc": 397.19999999999999, "running_tests": 0, "hostname": "hammercloud-ai-15.cern.ch", "tot_queued_jobs": 0, "mem_buffers": "239", "mem_without_bc": "560", "used_mem_HCpythonproc": 36.899999999999999, "used_mem": "2938", "used_mem_HCshellproc": 0.51900000000000002, "mem_cached": "2139", "timestamp": "2014/07/17 - 16:31:03"}, {"wa": "1.2", "submitting_tests": 0, "tot_running_jobs": 0, "cpu_load": "0.63 0.29 0.15 2/194 11025", "used_mem_proc": 405.69999999999999, "running_tests": 0, "hostname": "hammercloud-ai-15.cern.ch", "tot_queued_jobs": 0, "mem_buffers": "239", "mem_without_bc": "560", "used_mem_HCpythonproc": 36.200000000000003, "used_mem": "2938", "used_mem_HCshellproc": 0.53100000000000003, "mem_cached": "2140", "timestamp": "2014/07/17 - 16:41:01"}, {"wa": "1.2", "submitting_tests": 0, "tot_running_jobs": 0, "cpu_load": "0.06 0.10 0.10 4/194 11547", "used_mem_proc": 397.30000000000001, "running_tests": 0, "hostname": "hammercloud-ai-15.cern.ch", "tot_queued_jobs": 0, "mem_buffers": "239", "mem_without_bc": "559", "used_mem_HCpythonproc": 34.799999999999997, "used_mem": "2938", "used_mem_HCshellproc": 0.52300000000000002, "mem_cached": "2140", "timestamp": "2014/07/17 - 16:51:03"}, {"wa": "1.2", "submitting_tests": 0, "tot_running_jobs": 0, "cpu_load": "0.35 0.17 0.11 3/194 12053", "used_mem_proc": 407.89999999999998, "running_tests": 0, "hostname": "hammercloud-ai-15.cern.ch", "tot_queued_jobs": 0, "mem_buffers": "239", "mem_without_bc": "533", "used_mem_HCpythonproc": 36.899999999999999, "used_mem": "2912", "used_mem_HCshellproc": 0.52300000000000002, "mem_cached": "2140", "timestamp": "2014/07/17 - 17:01:02"}, {"wa": "1.2", "submitting_tests": 0, "tot_running_jobs": 0, "cpu_load": "0.04 0.09 0.08 2/194 12588", "used_mem_proc": 408.10000000000002, "running_tests": 0, "hostname": "hammercloud-ai-15.cern.ch", "tot_queued_jobs": 0, "mem_buffers": "239", "mem_without_bc": "560", "used_mem_HCpythonproc": 36.399999999999999, "used_mem": "2939", "used_mem_HCshellproc": 0.52300000000000002, "mem_cached": "2140", "timestamp": "2014/07/17 - 17:11:02"}, {"wa": "1.2", "submitting_tests": 0, "tot_running_jobs": 0, "cpu_load": "0.22 0.14 0.10 4/196 13139", "used_mem_proc": 452.5, "running_tests": 0, "hostname": "hammercloud-ai-15.cern.ch", "tot_queued_jobs": 0, "mem_buffers": "239", "mem_without_bc": "587", "used_mem_HCpythonproc": 36.0, "used_mem": "2962", "used_mem_HCshellproc": 0.51400000000000001, "mem_cached": "2142", "timestamp": "2014/07/17 - 17:21:02"}, {"wa": "1.2", "submitting_tests": 0, "tot_running_jobs": 0, "cpu_load": "0.10 0.12 0.10 2/193 14514", "used_mem_proc": 397.10000000000002, "running_tests": 0, "hostname": "hammercloud-ai-15.cern.ch", "tot_queued_jobs": 0, "mem_buffers": "239", "mem_without_bc": "558", "used_mem_HCpythonproc": 36.399999999999999, "used_mem": "2940", "used_mem_HCshellproc": 0.52300000000000002, "mem_cached": "2143", "timestamp": "2014/07/17 - 17:31:02"}, {"wa": "1.2", "submitting_tests": 0, "tot_running_jobs": 0, "cpu_load": "0.22 0.07 0.07 3/193 15007", "used_mem_proc": 397.19999999999999, "running_tests": 0, "hostname": "hammercloud-ai-15.cern.ch", "tot_queued_jobs": 0, "mem_buffers": "239", "mem_without_bc": "559", "used_mem_HCpythonproc": 36.399999999999999, "used_mem": "2942", "used_mem_HCshellproc": 0.52700000000000002, "mem_cached": "2143", "timestamp": "2014/07/17 - 17:41:02"}, {"wa": "1.2", "submitting_tests": 0, "tot_running_jobs": 0, "cpu_load": "0.06 0.05 0.05 3/189 15505", "used_mem_proc": 368.80000000000001, "running_tests": 0, "hostname": "hammercloud-ai-15.cern.ch", "tot_queued_jobs": 0, "mem_buffers": "239", "mem_without_bc": "532", "used_mem_HCpythonproc": 36.5, "used_mem": "2914", "used_mem_HCshellproc": 0.59899999999999998, "mem_cached": "2143", "timestamp": "2014/07/17 - 17:51:02"}, {"wa": "1.2", "submitting_tests": 0, "tot_running_jobs": 0, "cpu_load": "0.30 0.12 0.09 3/189 16010", "used_mem_proc": 378.60000000000002, "running_tests": 0, "hostname": "hammercloud-ai-15.cern.ch", "tot_queued_jobs": 0, "mem_buffers": "239", "mem_without_bc": "532", "used_mem_HCpythonproc": 36.600000000000001, "used_mem": "2914", "used_mem_HCshellproc": 0.59899999999999998, "mem_cached": "2143", "timestamp": "2014/07/17 - 18:01:02"}, {"wa": "1.2", "submitting_tests": 0, "tot_running_jobs": 0, "cpu_load": "0.08 0.15 0.11 3/189 17422", "used_mem_proc": 380.69999999999999, "running_tests": 0, "hostname": "hammercloud-ai-15.cern.ch", "tot_queued_jobs": 0, "mem_buffers": "239", "mem_without_bc": "507", "used_mem_HCpythonproc": 37.200000000000003, "used_mem": "2890", "used_mem_HCshellproc": 0.59499999999999997, "mem_cached": "2144", "timestamp": "2014/07/17 - 18:11:02"}, {"wa": "1.2", "submitting_tests": 0, "tot_running_jobs": 0, "cpu_load": "0.23 0.15 0.10 2/189 17962", "used_mem_proc": 368.89999999999998, "running_tests": 0, "hostname": "hammercloud-ai-15.cern.ch", "tot_queued_jobs": 0, "mem_buffers": "239", "mem_without_bc": "530", "used_mem_HCpythonproc": 36.600000000000001, "used_mem": "2913", "used_mem_HCshellproc": 0.59499999999999997, "mem_cached": "2144", "timestamp": "2014/07/17 - 18:21:03"}, {"wa": "1.2", "submitting_tests": 0, "tot_running_jobs": 0, "cpu_load": "0.30 0.14 0.10 2/190 18459", "used_mem_proc": 368.80000000000001, "running_tests": 0, "hostname": "hammercloud-ai-15.cern.ch", "tot_queued_jobs": 0, "mem_buffers": "239", "mem_without_bc": "530", "used_mem_HCpythonproc": 32.5, "used_mem": "2914", "used_mem_HCshellproc": 0.59499999999999997, "mem_cached": "2144", "timestamp": "2014/07/17 - 18:31:01"}, {"wa": "1.2", "submitting_tests": 0, "tot_running_jobs": 0, "cpu_load": "0.13 0.16 0.11 3/190 18955", "used_mem_proc": 369.0, "running_tests": 0, "hostname": "hammercloud-ai-15.cern.ch", "tot_queued_jobs": 0, "mem_buffers": "239", "mem_without_bc": "532", "used_mem_HCpythonproc": 35.5, "used_mem": "2915", "used_mem_HCshellproc": 0.59499999999999997, "mem_cached": "2144", "timestamp": "2014/07/17 - 18:41:02"}, {"wa": "1.2", "submitting_tests": 0, "tot_running_jobs": 0, "cpu_load": "0.18 0.22 0.13 4/192 20941", "used_mem_proc": 370.39999999999998, "running_tests": 0, "hostname": "hammercloud-ai-15.cern.ch", "tot_queued_jobs": 0, "mem_buffers": "239", "mem_without_bc": "522", "used_mem_HCpythonproc": 37.200000000000003, "used_mem": "2905", "used_mem_HCshellproc": 0.59899999999999998, "mem_cached": "2145", "timestamp": "2014/07/17 - 18:51:02"}, {"wa": "1.2", "submitting_tests": 0, "tot_running_jobs": 0, "cpu_load": "0.26 0.13 0.10 2/190 21443", "used_mem_proc": 364.60000000000002, "running_tests": 0, "hostname": "hammercloud-ai-15.cern.ch", "tot_queued_jobs": 0, "mem_buffers": "239", "mem_without_bc": "526", "used_mem_HCpythonproc": 30.699999999999999, "used_mem": "2909", "used_mem_HCshellproc": 0.59899999999999998, "mem_cached": "2145", "timestamp": "2014/07/17 - 19:01:01"}, {"wa": "1.2", "submitting_tests": 0, "tot_running_jobs": 0, "cpu_load": "0.06 0.08 0.08 2/190 21981", "used_mem_proc": 362.60000000000002, "running_tests": 0, "hostname": "hammercloud-ai-15.cern.ch", "tot_queued_jobs": 0, "mem_buffers": "239", "mem_without_bc": "523", "used_mem_HCpythonproc": 32.700000000000003, "used_mem": "2906", "used_mem_HCshellproc": 0.59499999999999997, "mem_cached": "2145", "timestamp": "2014/07/17 - 19:11:02"}, {"wa": "1.2", "submitting_tests": 0, "tot_running_jobs": 0, "cpu_load": "0.51 0.17 0.11 3/190 22520", "used_mem_proc": 391.0, "running_tests": 0, "hostname": "hammercloud-ai-15.cern.ch", "tot_queued_jobs": 0, "mem_buffers": "239", "mem_without_bc": "518", "used_mem_HCpythonproc": 25.199999999999999, "used_mem": "2903", "used_mem_HCshellproc": 0.59099999999999997, "mem_cached": "2145", "timestamp": "2014/07/17 - 19:21:02"}, {"wa": "1.2", "submitting_tests": 0, "tot_running_jobs": 0, "cpu_load": "0.27 0.13 0.10 5/193 23162", "used_mem_proc": 425.39999999999998, "running_tests": 0, "hostname": "hammercloud-ai-15.cern.ch", "tot_queued_jobs": 0, "mem_buffers": "239", "mem_without_bc": "572", "used_mem_HCpythonproc": 37.200000000000003, "used_mem": "2956", "used_mem_HCshellproc": 0.59499999999999997, "mem_cached": "2145", "timestamp": "2014/07/17 - 19:31:02"}, {"wa": "1.2", "submitting_tests": 0, "tot_running_jobs": 0, "cpu_load": "0.23 0.15 0.11 3/190 24392", "used_mem_proc": 366.10000000000002, "running_tests": 0, "hostname": "hammercloud-ai-15.cern.ch", "tot_queued_jobs": 0, "mem_buffers": "239", "mem_without_bc": "527", "used_mem_HCpythonproc": 34.600000000000001, "used_mem": "2912", "used_mem_HCshellproc": 0.59899999999999998, "mem_cached": "2146", "timestamp": "2014/07/17 - 19:41:03"}, {"wa": "1.2", "submitting_tests": 0, "tot_running_jobs": 0, "cpu_load": "0.28 0.11 0.08 5/190 24882", "used_mem_proc": 365.5, "running_tests": 0, "hostname": "hammercloud-ai-15.cern.ch", "tot_queued_jobs": 0, "mem_buffers": "239", "mem_without_bc": "528", "used_mem_HCpythonproc": 36.600000000000001, "used_mem": "2913", "used_mem_HCshellproc": 0.59499999999999997, "mem_cached": "2146", "timestamp": "2014/07/17 - 19:51:02"}, {"wa": "1.2", "submitting_tests": 0, "tot_running_jobs": 0, "cpu_load": "0.06 0.05 0.06 5/190 25388", "used_mem_proc": 365.5, "running_tests": 0, "hostname": "hammercloud-ai-15.cern.ch", "tot_queued_jobs": 0, "mem_buffers": "239", "mem_without_bc": "528", "used_mem_HCpythonproc": 36.5, "used_mem": "2914", "used_mem_HCshellproc": 0.59499999999999997, "mem_cached": "2146", "timestamp": "2014/07/17 - 20:01:02"}, {"wa": "1.2", "submitting_tests": 0, "tot_running_jobs": 0, "cpu_load": "0.04 0.07 0.07 2/190 25921", "used_mem_proc": 376.39999999999998, "running_tests": 0, "hostname": "hammercloud-ai-15.cern.ch", "tot_queued_jobs": 0, "mem_buffers": "239", "mem_without_bc": "529", "used_mem_HCpythonproc": 36.600000000000001, "used_mem": "2915", "used_mem_HCshellproc": 0.59099999999999997, "mem_cached": "2146", "timestamp": "2014/07/17 - 20:11:02"}, {"wa": "1.2", "submitting_tests": 0, "tot_running_jobs": 0, "cpu_load": "0.27 0.33 0.19 2/190 27332", "used_mem_proc": 365.80000000000001, "running_tests": 0, "hostname": "hammercloud-ai-15.cern.ch", "tot_queued_jobs": 0, "mem_buffers": "239", "mem_without_bc": "528", "used_mem_HCpythonproc": 35.899999999999999, "used_mem": "2914", "used_mem_HCshellproc": 0.59899999999999998, "mem_cached": "2147", "timestamp": "2014/07/17 - 20:21:02"}, {"wa": "1.2", "submitting_tests": 0, "tot_running_jobs": 0, "cpu_load": "0.32 0.14 0.14 2/190 27828", "used_mem_proc": 365.80000000000001, "running_tests": 0, "hostname": "hammercloud-ai-15.cern.ch", "tot_queued_jobs": 0, "mem_buffers": "239", "mem_without_bc": "527", "used_mem_HCpythonproc": 29.899999999999999, "used_mem": "2913", "used_mem_HCshellproc": 0.59899999999999998, "mem_cached": "2147", "timestamp": "2014/07/17 - 20:31:01"}, {"wa": "1.2", "submitting_tests": 0, "tot_running_jobs": 0, "cpu_load": "0.04 0.07 0.09 4/191 28331", "tot_queued_jobs": 0, "running_tests": 0, "hostname": "hammercloud-ai-15.cern.ch", "used_mem_proc": 378.80000000000001, "mem_buffers": "239", "mem_without_bc": "507", "used_mem_HCpythonproc": 46.399999999999999, "used_mem": "2892", "used_mem_HCshellproc": 0.59499999999999997, "mem_cached": "2147", "timestamp": "2014/07/17 - 20:41:03"}, {"submitting_tests": 0, "wa": "1.2", "tot_running_jobs": 0, "cpu_load": "0.48 0.14 0.10 2/190 28812", "tot_queued_jobs": 0, "running_tests": 0, "hostname": "hammercloud-ai-15.cern.ch", "used_mem_proc": 366.0, "mem_buffers": "239", "mem_without_bc": "527", "used_mem_HCpythonproc": 32.700000000000003, "used_mem": "2914", "used_mem_HCshellproc": 0.59099999999999997, "mem_cached": "2147", "timestamp": "2014/07/17 - 20:51:01"}, {"wa": "1.2", "used_mem_proc": 366.0, "hostname": "hammercloud-ai-15.cern.ch", "mem_buffers": "239", "cpu_load": "0.34 0.31 0.17 2/190 30200", "mem_without_bc": "527", "used_mem_HCpythonproc": 35.200000000000003, "submitting_tests": 0, "tot_running_jobs": 0, "used_mem": "2914", "tot_queued_jobs": 0, "running_tests": 0, "used_mem_HCshellproc": 0.59499999999999997, "mem_cached": "2148", "timestamp": "2014/07/17 - 21:01:02"}]